terraform_module_bundler/__init__.py
terraform_module_bundler/bundle.py
terraform_module_bundler/main.py
terraform_module_bundler-0.0.1.dist-info/METADATA
terraform_module_bundler-0.0.1.dist-info/WHEEL
terraform_module_bundler-0.0.1.dist-info/entry_points.txt
terraform_module_bundler-0.0.1.dist-info/top_level.txt
terraform_module_bundler-0.0.1.dist-info/RECORD
